ceshiabogger/__init__.py
ceshiabogger/timing_print_hello.py
ceshiabogger-0.1.0.dist-info/WHEEL
ceshiabogger-0.1.0.dist-info/METADATA
ceshiabogger-0.1.0.dist-info/RECORD
