Metadata-Version: 2.1
Name: ceshiabogger
Version: 0.1.0
Summary: 
Author: laowang
Author-email: 847063657@qq.com
Requires-Python: >=3.10,<4.0
Classifier: Programming Language :: Python :: 3
Classifier: Programming Language :: Python :: 3.10
Requires-Dist: PyMySQL (>=1.0.2,<2.0.0)
Requires-Dist: fastapi-utils (>=0.2.1,<0.3.0)
